deepstream/__init__.py
deepstream/_version.py
deepstream/deepstream.py
deepstream/utils.py
deepstream-0.1.dist-info/METADATA
deepstream-0.1.dist-info/WHEEL
deepstream-0.1.dist-info/top_level.txt
deepstream-0.1.dist-info/RECORD
